{
  "alert_id": "7704d934-d470-4e5d-8a61-32b82c65638c",
  "severity": "critical",
  "service": "demo",
  "score": 100.0,
  "timestamp": 0.0,
  "evidence_window": {
    "templates_preview": [
      "tid=6709: APPCHILD <HEX> <DATE> <NODE> <TS> <NODE> RAS APP FATAL ciod: Error creating node map from file map.d...",
      "tid=6290: - <HEX> <DATE> UNKNOWN_LOCATION <TS> UNKNOWN_LOCATION NULL DISCOVERY INFO New ido chip inserted into...",
      "tid=6971: KERNMNTF <HEX> <DATE> <NODE> <TS> <NODE> RAS KERNEL FATAL Lustre mount FAILED : bglio290 : block_id ...",
      "tid=1703: - <HEX> <DATE> <NODE> <TS> <NODE> RAS KERNEL FATAL uncorrectable error detected in EDRAM bank <NUM>....",
      "tid=7339: KERNMNTF <HEX> <DATE> <NODE> <TS> <NODE> RAS KERNEL FATAL Lustre mount FAILED : bglio60 : block_id :..."
    ],
    "token_count": 10,
    "start_ts": 0.0,
    "end_ts": 0.0
  },
  "model_name": "baseline",
  "threshold": 0.3303178258763508,
  "meta": {
    "stream_key": "demo:warmup-session",
    "is_anomaly": true,
    "window_size": 10,
    "label": 0,
    "emit_index": 15
  },
  "explanation": null,
  "semantic_similarity": null,
  "top_similar_events": null,
  "evidence_tokens": null
}